code_inspection_utils/__init__.py
code_inspection_utils/inject_trace_statements.py
code_inspection_utils/manager.py
code_inspection_utils/conf/config.yaml
code_inspection_utils-0.1.0.dist-info/AUTHORS.rst
code_inspection_utils-0.1.0.dist-info/LICENSE
code_inspection_utils-0.1.0.dist-info/METADATA
code_inspection_utils-0.1.0.dist-info/WHEEL
code_inspection_utils-0.1.0.dist-info/entry_points.txt
code_inspection_utils-0.1.0.dist-info/top_level.txt
code_inspection_utils-0.1.0.dist-info/RECORD
